<?xml version = '1.0' encoding = 'UTF-8'?>
<TableProxyOraclev20c class="oracle.dbtools.crest.model.design.storage.oracle.v20c.TableProxyOraclev20c" name="bloque_hora" directorySegmentName="seg_0" id="F6472C54-DE42-FBC7-4D13-BFC7B5FA06CC">
<createdBy>katsup</createdBy>
<createdTime>2025-09-12 02:26:30 UTC</createdTime>
<ownerDesignName>Diagrama ER - MediConnect</ownerDesignName>
<logging>YES</logging>
<partitionedRowMovement>DISABLE</partitionedRowMovement>
<temporaryChanged>false</temporaryChanged>
<accessDriverType>oracle_loader</accessDriverType>
<rejectLimit></rejectLimit>
<columnProxies itemClass="oracle.dbtools.crest.model.design.storage.oracle.v12c.ColumnProxyOraclev12c">
<ColumnProxy name="fin" id="1C9853CA-C150-15A0-2449-FD891FB4F97C">
<createdBy>katsup</createdBy>
<createdTime>2025-09-12 02:26:31 UTC</createdTime>
<ownerDesignName>Diagrama ER - MediConnect</ownerDesignName>
</ColumnProxy>
<ColumnProxy name="inicio" id="52A17B62-5A2B-ADEC-7A2F-4671931B285A">
<createdBy>katsup</createdBy>
<createdTime>2025-09-12 02:26:31 UTC</createdTime>
<ownerDesignName>Diagrama ER - MediConnect</ownerDesignName>
</ColumnProxy>
<ColumnProxy name="disponible" id="8A9EC095-5CB2-A2B1-1E6E-8FAC5DCEC2E2">
<createdBy>katsup</createdBy>
<createdTime>2025-09-12 02:26:31 UTC</createdTime>
<ownerDesignName>Diagrama ER - MediConnect</ownerDesignName>
<defaultValue>1</defaultValue>
</ColumnProxy>
<ColumnProxy name="id_bloque" id="B8B9B796-8262-28AA-F522-E8F605D5100A">
<createdBy>katsup</createdBy>
<createdTime>2025-09-12 02:26:31 UTC</createdTime>
<ownerDesignName>Diagrama ER - MediConnect</ownerDesignName>
<autoIncrementDDL>IDENTITY_CLAUSE</autoIncrementDDL>
</ColumnProxy>
<ColumnProxy name="id_agenda" id="E42AC809-CD78-F40A-A08B-13116E7FF76B">
<createdBy>katsup</createdBy>
<createdTime>2025-09-12 02:26:31 UTC</createdTime>
<ownerDesignName>Diagrama ER - MediConnect</ownerDesignName>
</ColumnProxy>
</columnProxies>
<foreignKeys>
<ForeignKey class="oracle.dbtools.crest.model.design.storage.oracle.v10g.FKProxyOraclev10g" name="fk_bloque_agenda" id="0BDB8AD7-7066-ADFF-D279-05D4A665CDB7">
<createdBy>katsup</createdBy>
<createdTime>2025-09-12 02:26:31 UTC</createdTime>
<ownerDesignName>Diagrama ER - MediConnect</ownerDesignName>
</ForeignKey>
</foreignKeys>
<primaryKeys>
<PrimaryKey class="oracle.dbtools.crest.model.design.storage.oracle.v10g.PKProxyOraclev10g" name="bloque_hora_PK" id="C84EE6B5-C746-BCF1-5AC3-49A4F74E5EB7">
<createdBy>katsup</createdBy>
<createdTime>2025-09-12 02:26:31 UTC</createdTime>
<ownerDesignName>Diagrama ER - MediConnect</ownerDesignName>
<indexSort>SORTED</indexSort>
</PrimaryKey>
</primaryKeys>
<tableCheckConstraints itemClass="oracle.dbtools.crest.model.design.storage.oracle.TableCheckConstraintOracle">
<TableCheckConstraint name="chk_bloque_rango" id="2B507C72-155A-0A4B-E826-64AAF46C849C">
<createdBy>katsup</createdBy>
<createdTime>2025-09-12 02:26:31 UTC</createdTime>
<ownerDesignName>Diagrama ER - MediConnect</ownerDesignName>
<nameChanged>true</nameChanged>
</TableCheckConstraint>
<TableCheckConstraint name="chk_bloque_disponible" id="4FCEEDD1-0324-E19B-F696-FEC9908C1E8F">
<createdBy>katsup</createdBy>
<createdTime>2025-09-12 02:26:31 UTC</createdTime>
<ownerDesignName>Diagrama ER - MediConnect</ownerDesignName>
<nameChanged>true</nameChanged>
</TableCheckConstraint>
</tableCheckConstraints>
<uniqueKeys>
<UniqueKey class="oracle.dbtools.crest.model.design.storage.oracle.v10g.UniqueOraclev10g" name="uq_bloque_agenda_inicio" id="B72EBC61-5B32-0E9B-655D-20922E4ED338">
<createdBy>katsup</createdBy>
<createdTime>2025-09-12 02:26:31 UTC</createdTime>
<ownerDesignName>Diagrama ER - MediConnect</ownerDesignName>
<indexSort>SORTED</indexSort>
</UniqueKey>
</uniqueKeys>
</TableProxyOraclev20c>